pelican_advance_embed_tweet/__init__.py
pelican_advance_embed_tweet/advance_embed_tweet.py
pelican_advance_embed_tweet-1.1.3.dist-info/DESCRIPTION.rst
pelican_advance_embed_tweet-1.1.3.dist-info/METADATA
pelican_advance_embed_tweet-1.1.3.dist-info/RECORD
pelican_advance_embed_tweet-1.1.3.dist-info/WHEEL
pelican_advance_embed_tweet-1.1.3.dist-info/metadata.json
pelican_advance_embed_tweet-1.1.3.dist-info/top_level.txt
